CHANGELOG.txt
LICENSE.txt
MANIFEST.in
README.txt
requirements.txt
setup.py
User_Properties_SDK.egg-info/PKG-INFO
User_Properties_SDK.egg-info/SOURCES.txt
User_Properties_SDK.egg-info/dependency_links.txt
User_Properties_SDK.egg-info/requires.txt
User_Properties_SDK.egg-info/top_level.txt
env/bin/activate_this.py
env/bin/rst2html.py
env/bin/rst2html4.py
env/bin/rst2html5.py
env/bin/rst2latex.py
env/bin/rst2man.py
env/bin/rst2odt.py
env/bin/rst2odt_prepstyles.py
env/bin/rst2pseudoxml.py
env/bin/rst2s5.py
env/bin/rst2xetex.py
env/bin/rst2xml.py
env/bin/rstpep2html.py
env/lib/python2.7/os.py
env/lib/python2.7/site.py
env/lib/python2.7/site-packages/_virtualenv.py
env/lib/python2.7/site-packages/easy_install.py
env/lib/python2.7/site-packages/pyparsing.py
env/lib/python2.7/site-packages/six.py
env/lib/python2.7/site-packages/Pygments-2.5.2.dist-info/entry_points.txt
env/lib/python2.7/site-packages/Pygments-2.5.2.dist-info/top_level.txt
env/lib/python2.7/site-packages/bleach/__init__.py
env/lib/python2.7/site-packages/bleach/callbacks.py
env/lib/python2.7/site-packages/bleach/html5lib_shim.py
env/lib/python2.7/site-packages/bleach/linkifier.py
env/lib/python2.7/site-packages/bleach/sanitizer.py
env/lib/python2.7/site-packages/bleach/utils.py
env/lib/python2.7/site-packages/bleach-3.3.0.dist-info/top_level.txt
env/lib/python2.7/site-packages/bleach/_vendor/__init__.py
env/lib/python2.7/site-packages/bleach/_vendor/vendor.txt
env/lib/python2.7/site-packages/bleach/_vendor/Django-1.11.29.dist-info/entry_points.txt
env/lib/python2.7/site-packages/bleach/_vendor/Django-1.11.29.dist-info/top_level.txt
env/lib/python2.7/site-packages/bleach/_vendor/django/__init__.py
env/lib/python2.7/site-packages/bleach/_vendor/django/core/__init__.py
env/lib/python2.7/site-packages/bleach/_vendor/django/core/validators.py
env/lib/python2.7/site-packages/bleach/_vendor/html5lib/__init__.py
env/lib/python2.7/site-packages/bleach/_vendor/html5lib/_ihatexml.py
env/lib/python2.7/site-packages/bleach/_vendor/html5lib/_inputstream.py
env/lib/python2.7/site-packages/bleach/_vendor/html5lib/_tokenizer.py
env/lib/python2.7/site-packages/bleach/_vendor/html5lib/_utils.py
env/lib/python2.7/site-packages/bleach/_vendor/html5lib/constants.py
env/lib/python2.7/site-packages/bleach/_vendor/html5lib/html5parser.py
env/lib/python2.7/site-packages/bleach/_vendor/html5lib/serializer.py
env/lib/python2.7/site-packages/bleach/_vendor/html5lib-1.1.dist-info/top_level.txt
env/lib/python2.7/site-packages/bleach/_vendor/html5lib/_trie/__init__.py
env/lib/python2.7/site-packages/bleach/_vendor/html5lib/_trie/_base.py
env/lib/python2.7/site-packages/bleach/_vendor/html5lib/_trie/py.py
env/lib/python2.7/site-packages/certifi-2020.12.5.dist-info/top_level.txt
env/lib/python2.7/site-packages/chardet-4.0.0.dist-info/entry_points.txt
env/lib/python2.7/site-packages/chardet-4.0.0.dist-info/top_level.txt
env/lib/python2.7/site-packages/docutils-0.17.1.dist-info/COPYING.txt
env/lib/python2.7/site-packages/docutils-0.17.1.dist-info/top_level.txt
env/lib/python2.7/site-packages/failsafe-2.4.3.dist-info/top_level.txt
env/lib/python2.7/site-packages/glogger-1.3.4.dist-info/top_level.txt
env/lib/python2.7/site-packages/gtransport-0.2.10.dist-info/top_level.txt
env/lib/python2.7/site-packages/idna-2.10.dist-info/top_level.txt
env/lib/python2.7/site-packages/packaging-20.9.dist-info/top_level.txt
env/lib/python2.7/site-packages/pip-20.3.4.dist-info/LICENSE.txt
env/lib/python2.7/site-packages/pip-20.3.4.dist-info/entry_points.txt
env/lib/python2.7/site-packages/pip-20.3.4.dist-info/top_level.txt
env/lib/python2.7/site-packages/pkginfo-1.7.0.dist-info/LICENSE.txt
env/lib/python2.7/site-packages/pkginfo-1.7.0.dist-info/entry_points.txt
env/lib/python2.7/site-packages/pkginfo-1.7.0.dist-info/top_level.txt
env/lib/python2.7/site-packages/power_switch-1.1.2.dist-info/top_level.txt
env/lib/python2.7/site-packages/pyparsing-2.4.7.dist-info/top_level.txt
env/lib/python2.7/site-packages/readme_renderer-29.0.dist-info/entry_points.txt
env/lib/python2.7/site-packages/readme_renderer-29.0.dist-info/top_level.txt
env/lib/python2.7/site-packages/requests-2.25.1.dist-info/top_level.txt
env/lib/python2.7/site-packages/requests_toolbelt-0.9.1.dist-info/top_level.txt
env/lib/python2.7/site-packages/setuptools-44.1.1.dist-info/dependency_links.txt
env/lib/python2.7/site-packages/setuptools-44.1.1.dist-info/entry_points.txt
env/lib/python2.7/site-packages/setuptools-44.1.1.dist-info/top_level.txt
env/lib/python2.7/site-packages/six-1.16.0.dist-info/top_level.txt
env/lib/python2.7/site-packages/statsd-3.3.0.dist-info/top_level.txt
env/lib/python2.7/site-packages/structlog-20.1.0.dist-info/top_level.txt
env/lib/python2.7/site-packages/tqdm-4.60.0.dist-info/entry_points.txt
env/lib/python2.7/site-packages/tqdm-4.60.0.dist-info/top_level.txt
env/lib/python2.7/site-packages/twine-1.15.0.dist-info/entry_points.txt
env/lib/python2.7/site-packages/twine-1.15.0.dist-info/top_level.txt
env/lib/python2.7/site-packages/ujson-2.0.3.dist-info/LICENSE.txt
env/lib/python2.7/site-packages/ujson-2.0.3.dist-info/top_level.txt
env/lib/python2.7/site-packages/urllib3-1.26.4.dist-info/LICENSE.txt
env/lib/python2.7/site-packages/urllib3-1.26.4.dist-info/top_level.txt
env/lib/python2.7/site-packages/webencodings-0.5.1.dist-info/top_level.txt
env/lib/python2.7/site-packages/wheel-0.36.2.dist-info/LICENSE.txt
env/lib/python2.7/site-packages/wheel-0.36.2.dist-info/entry_points.txt
env/lib/python2.7/site-packages/wheel-0.36.2.dist-info/top_level.txt
